svg2gif/__init__.py
svg2gif/core.py
svg2gif-0.1.0.dist-info/METADATA
svg2gif-0.1.0.dist-info/WHEEL
svg2gif-0.1.0.dist-info/top_level.txt
svg2gif-0.1.0.dist-info/RECORD
