Metadata-Version: 2.4
Name: svg2gif
Version: 0.1.0
Summary: Convert svg file to a gif file
Author: Christopher Hirschauer
License: MIT
Project-URL: Homepage, https://github.com/74Thirsty/svg2gif
Requires-Python: >=3.9
